agent_handler_sdk/__init__.py
agent_handler_sdk/auth.py
agent_handler_sdk/cli.py
agent_handler_sdk/connector.py
agent_handler_sdk/eval_types.py
agent_handler_sdk/exceptions.py
agent_handler_sdk/invocation.py
agent_handler_sdk/registry.py
agent_handler_sdk/templates/connector/README.md.tpl
agent_handler_sdk/templates/connector/evals.json.tpl
agent_handler_sdk/templates/connector/handlers.py.tpl
agent_handler_sdk/templates/connector/init.py.tpl
agent_handler_sdk/templates/connector/metadata.yaml.tpl
agent_handler_sdk/templates/connector/pyproject.toml.tpl
agent_handler_sdk/templates/connector/test_handlers.py.tpl
agent_handler_sdk/templates/evals/models.py
agent_handler_sdk/tool.py
agent_handler_sdk/utils.py
agent_handler_sdk-0.1.5.dist-info/METADATA
agent_handler_sdk-0.1.5.dist-info/WHEEL
agent_handler_sdk-0.1.5.dist-info/entry_points.txt
agent_handler_sdk-0.1.5.dist-info/RECORD
