Metadata-Version: 2.3
Name: agent-handler-sdk
Version: 0.1.5
Summary: Agent Handler SDK for defining and invoking LLM tools
Author: David Dalmaso
Author-email: david.dalmaso@merge.dev
Requires-Python: >=3.10
Classifier: Programming Language :: Python :: 3
Classifier: Programming Language :: Python :: 3.10
Classifier: Programming Language :: Python :: 3.11
Classifier: Programming Language :: Python :: 3.12
Classifier: Programming Language :: Python :: 3.13
Requires-Dist: jsonschema (>=4.0,<5.0)
Requires-Dist: pydantic (>=2.0,<3.0)
